pyMAVLinCS/__init__.py
pyMAVLinCS/mavecstra.py
pyMAVLinCS/mavtypes.py
pyMAVLinCS/mission_control_code.py
pyMAVLinCS/setup_logger.py
pymavlincs-1.0.5.dist-info/licenses/LICENSE
pymavlincs-1.0.5.dist-info/METADATA
pymavlincs-1.0.5.dist-info/WHEEL
pymavlincs-1.0.5.dist-info/top_level.txt
pymavlincs-1.0.5.dist-info/RECORD
