Metadata-Version: 2.4
Name: pyMAVLinCS
Version: 1.0.5
Summary: Python API for autonomous drone control based on pymavlink
Author-email: Noah Redon <redonnoah.cs@gmail.com>
License: GPL-3.0-or-later
Requires-Python: >=3.8
License-File: LICENSE
Requires-Dist: pymavlink>=2.4.49
Requires-Dist: pyserial
Requires-Dist: geopy
Dynamic: license-file
